ddtig/__init__.py
ddtig/application/__init__.py
ddtig/application/model_handler.py
ddtig/application/test_pipeline.py
ddtig/domain/__init__.py
ddtig/domain/model_analyser/__init__.py
ddtig/domain/model_analyser/base/__init__.py
ddtig/domain/model_analyser/base/tree.py
ddtig/domain/model_analyser/mut/__init__.py
ddtig/domain/model_analyser/mut/data_model.py
ddtig/domain/model_analyser/mut/hoeffding_tree.py
ddtig/domain/model_analyser/surrogate/__init__.py
ddtig/domain/model_analyser/surrogate/eqclass_handler.py
ddtig/domain/model_analyser/surrogate/interval.py
ddtig/domain/test_generator/__init__.py
ddtig/domain/test_generator/testcomp.py
ddtig/domain/test_generator/testgen.py
ddtig/infrastructure/__init__.py
ddtig/infrastructure/test_logger.py
ddtig/infrastructure/utils.py
ddtig/user_interface/__init__.py
ddtig/user_interface/reqs_handler.py
ddtig/user_interface/specs_handler.py
data_driven_test_input_generator-0.1.0.dist-info/METADATA
data_driven_test_input_generator-0.1.0.dist-info/WHEEL
data_driven_test_input_generator-0.1.0.dist-info/licenses/LICENSE
data_driven_test_input_generator-0.1.0.dist-info/RECORD
