Metadata-Version: 2.4
Name: data_driven_test_input_generator
Version: 0.1.0
Summary: A Test Input Generation Framework based on Data-Driven Models for Cyber-Physical Systems
Project-URL: Homepage, https://github.com/flowcean/data-driven-test-input-generator
Project-URL: Issues, https://github.com/flowcean/data-driven-test-input-generator/issues
Author-email: Linh Ngoc Le <linh.le@tuhh.de>
License-Expression: BSD-3-Clause
License-File: LICENSE
Classifier: License :: OSI Approved :: BSD License
Classifier: Operating System :: OS Independent
Classifier: Programming Language :: Python :: 3
Classifier: Programming Language :: Python :: 3.13
Classifier: Topic :: Software Development :: Libraries :: Python Modules
Requires-Python: <4.0,>=3.13
Requires-Dist: flowcean==0.7.0b1
Requires-Dist: pyyaml>=6.0.2
Requires-Dist: river>=0.22.0
Requires-Dist: scikit-learn>=1.6.1
Requires-Dist: tabulate>=0.9.0
